Workbook

Sheet Delivery Board
A1: SportIQ — Delivery Board & Roadmap
A2: Delivered dates are REAL (git history, first commit 2026-07-28). Dates from 2026-08-05 onward are PROPOSED. Updated 2026-08-04.
A4: Epic | B4: Feature / Deliverable | C4: Status | D4: Stream | E4: Start | F4: End | G4: Notes | H4: 27 Jul | I4: 03 Aug | J4: 10 Aug | K4: 17 Aug | L4: 24 Aug | M4: 31 Aug | N4: 07 Sep | O4: 14 Sep | P4: 21 Sep | Q4: 28 Sep | R4: EpicKey (helper)
A5: E1 Foundation | B5: PRD/TDD, repo, CLAUDE.md guidance | C5: Done | D5: Platform | E5: 46231 | F5: 46231 | G5: First commit | R5: =IF($A5<>"",$A5,R4) -> E1 Foundation
B6: FastAPI scaffold, TDD §2.1 schema, Alembic | C6: Done | D6: Platform | E6: 46231 | F6: 46232 | G6: All core tables | R6: =IF($A6<>"",$A6,R5) -> E1 Foundation
B7: Docker Compose (Postgres 16 + Redis 7) | C7: Done | D7: Platform | E7: 46231 | F7: 46231 | G7: Local dev only | R7: =IF($A7<>"",$A7,R6) -> E1 Foundation
B8: CI: pytest, ruff, black, tsc | C8: Done | D8: Platform | E8: 46233 | F8: 46233 | G8: GitHub Actions, green | R8: =IF($A8<>"",$A8,R7) -> E1 Foundation
A9: E2 Ingestion | B9: BallDontLie adapter (NBA) | C9: Done | D9: Data | E9: 46231 | F9: 46231 | G9: First real adapter | R9: =IF($A9<>"",$A9,R8) -> E2 Ingestion
B10: TheRundown adapter (odds) | C10: Done | D10: Data | E10: 46232 | F10: 46232 | G10: American->decimal | R10: =IF($A10<>"",$A10,R9) -> E2 Ingestion
B11: API-Football adapter (Pro tier) | C11: Done | D11: Data | E11: 46232 | F11: 46233 | G11: Fixtures/stats/injuries/H2H | R11: =IF($A11<>"",$A11,R10) -> E2 Ingestion
B12: Live scores + outcome settlement | C12: Done | D12: Data | E12: 46233 | F12: 46234 | G12: FixtureLiveState now written | R12: =IF($A12<>"",$A12,R11) -> E2 Ingestion
B13: Celery worker + beat actually running | C13: Done | D13: Data | E13: 46236 | F13: 46237 | G13: Never ran before this | R13: =IF($A13<>"",$A13,R12) -> E2 Ingestion
A14: E3 ML NBA | B14: Historical collection (6 seasons) | C14: Done | D14: ML | E14: 46231 | F14: 46232 | G14: ~14.5k games | R14: =IF($A14<>"",$A14,R13) -> E3 ML NBA
B15: XGBoost + isotonic, 16 features | C15: Done | D15: ML | E15: 46232 | F15: 46232 | G15: 68.57% vs 55.43% base | R15: =IF($A15<>"",$A15,R14) -> E3 ML NBA
B16: Big3/Top5 key-player availability | C16: Done | D16: ML | E16: 46232 | F16: 46233 | G16: Two-stage, leakage-guarded | R16: =IF($A16<>"",$A16,R15) -> E3 ML NBA
A17: E4 ML Football | B17: EPL + Brasileirao collection | C17: Done | D17: ML | E17: 46232 | F17: 46233 | G17: 7.6k game-log rows | R17: =IF($A17<>"",$A17,R16) -> E4 ML Football
B18: Two-layer Poisson -> XGBoost 1X2 | C18: Done | D18: ML | E18: 46233 | F18: 46233 | G18: 47.9% vs 46.5% base | R18: =IF($A18<>"",$A18,R17) -> E4 ML Football
B19: Elo, streaks, richer H2H | C19: Done | D19: ML | E19: 46233 | F19: 46233 | G19: 21 features | R19: =IF($A19<>"",$A19,R18) -> E4 ML Football
B20: Expand to 5 leagues (MLS/CSL/Scot) | C20: Done | D20: ML | E20: 46236 | F20: 46236 | G20: Fixed O/U bias | R20: =IF($A20<>"",$A20,R19) -> E4 ML Football
B21: Retrodiction for completed fixtures | C21: Done | D21: ML | E21: 46234 | F21: 46234 | G21: Leakage-safe path | R21: =IF($A21<>"",$A21,R20) -> E4 ML Football
A22: E5 ML Tennis | B22: BallDontLie ATP adapter | C22: Done | D22: ML | E22: 46235 | F22: 46235 | G22: ALL-STAR tier | R22: =IF($A22<>"",$A22,R21) -> E5 ML Tennis
B23: Collection + train (17.7k examples) | C23: Done | D23: ML | E23: 46235 | F23: 46235 | G23: 63.9% vs 62.2% rank base | R23: =IF($A23<>"",$A23,R22) -> E5 ML Tennis
B24: Fix target leakage (winner as player1) | C24: Done | D24: ML | E24: 46235 | F24: 46235 | G24: Caught pre-launch | R24: =IF($A24<>"",$A24,R23) -> E5 ML Tennis
B25: Retirements, tournament grouping | C25: Done | D25: ML | E25: 46236 | F25: 46236 | G25: VOID badge | R25: =IF($A25<>"",$A25,R24) -> E5 ML Tennis
B26: Kickoff refresh + live derivation | C26: Done | D26: Data | E26: 46237 | F26: 46237 | G26: 26->20 estimated | R26: =IF($A26<>"",$A26,R25) -> E5 ML Tennis
A27: E6 Picks | B27: GET /picks, EV + threshold logic | C27: Done | D27: Backend | E27: 46232 | F27: 46233 | G27: TDD §4.2 | R27: =IF($A27<>"",$A27,R26) -> E6 Picks
B28: Extra markets: DC, O/U goals, corners | C28: Done | D28: Backend | E28: 46234 | F28: 46235 | G28: Poisson-derived | R28: =IF($A28<>"",$A28,R27) -> E6 Picks
B29: Base-rate relative ranking | C29: Done | D29: Backend | E29: 46236 | F29: 46236 | G29: Replaced pure EV | R29: =IF($A29<>"",$A29,R28) -> E6 Picks
B30: GET /history + summary | C30: Done | D30: Backend | E30: 46236 | F30: 46236 | G30: Was a 501 stub | R30: =IF($A30<>"",$A30,R29) -> E6 Picks
A31: E7 Mobile | B31: Expo scaffold, 8 routes, API client | C31: Done | D31: Mobile | E31: 46233 | F31: 46234 | G31: Web + Android verified | R31: =IF($A31<>"",$A31,R30) -> E7 Mobile
B32: Auth, guest sessions, biometrics | C32: Done | D32: Mobile | E32: 46234 | F32: 46234 | G32: SecureStore JWT | R32: =IF($A32<>"",$A32,R31) -> E7 Mobile
B33: Fixture cards, verdicts, flags | C33: Done | D33: Mobile | E33: 46235 | F33: 46236 | G33: Real flag PNGs | R33: =IF($A33<>"",$A33,R32) -> E7 Mobile
B34: Picks UI rebuild (dropdowns, calendar) | C34: Done | D34: Mobile | E34: 46237 | F34: 46237 | G34: Per mockups | R34: =IF($A34<>"",$A34,R33) -> E7 Mobile
B35: Theme: light/dark/system, account-synced | C35: Done | D35: Mobile | E35: 46237 | F35: 46237 | G35: Cross-device verified | R35: =IF($A35<>"",$A35,R34) -> E7 Mobile
B36: Score on each team's row, badge aligned | C36: Done | D36: Mobile | E36: 46238 | F36: 46238 | G36: Per mockups; measured, not eyeballed | R36: =IF($A36<>"",$A36,R35) -> E7 Mobile
B37: Equal control widths, filters aligned | C37: Done | D37: Mobile | E37: 46238 | F37: 46238 | G37: Shared FILTER_TRIGGER_WIDTH | R37: =IF($A37<>"",$A37,R36) -> E7 Mobile
A38: E8 Model Quality | B38: Measure O/U signal (found ~none) | C38: Done | D38: ML | E38: 46236 | F38: 46236 | G38: corr +0.030 | R38: =IF($A38<>"",$A38,R37) -> E8 Model Quality
B39: Refute Negative Binomial premise | C39: Done | D39: ML | E39: 46236 | F39: 46236 | G39: var/mean = 1.003 | R39: =IF($A39<>"",$A39,R38) -> E8 Model Quality
B40: TheStatsAPI eval + xG integration | C40: Done | D40: ML | E40: 46237 | F40: 46237 | G40: xG r=+0.129 vs goals +0.062 | R40: =IF($A40<>"",$A40,R39) -> E8 Model Quality
B41: xG collection (5 leagues) | C41: Done | D41: ML | E41: 46237 | F41: 46238 | G41: Superseded by row 47: 5-league collection finished, 5.9k matches | R41: =IF($A41<>"",$A41,R40) -> E8 Model Quality
B42: Retrain + measure O/U buckets | C42: Done | D42: ML | E42: 46238 | F42: 46239 | G42: Superseded by rows 48/90: retrained, O/U buckets measured | R42: =IF($A42<>"",$A42,R41) -> E8 Model Quality
B43: League-identity features (partial pooling) | C43: Done | D43: ML | E43: 46239 | F43: 46241 | G43: Superseded by row 49: built, measured, NEGATIVE, disabled | R43: =IF($A43<>"",$A43,R42) -> E8 Model Quality
B44: Collect La Liga/Bundesliga/Ligue1 history | C44: Done | D44: ML | E44: 46240 | F44: 46243 | G44: Game logs collected for all 4 (+ Serie A). 7,028 fixtures, pool +81% | R44: =IF($A44<>"",$A44,R43) -> E8 Model Quality
B45: Lineups Scottish Prem + MLS, retrain | C45: Done | D45: ML | E45: 46241 | F45: 46244 | G45: DROPPED, not delivered: key-player features pruned, so lineups feed nothing | R45: =IF($A45<>"",$A45,R44) -> E8 Model Quality
B46: GO / NO-GO on Over-Under market | C46: Done | D46: ML | E46: 46244 | F46: 46244 | G46: GO. z=+2.96 p=0.0031 through the calibrated production path | J46: ◆ | R46: =IF($A46<>"",$A46,R45) -> E8 Model Quality
B47: xG collection complete (5 leagues, 5.9k matches) | C47: Done | D47: ML | E47: 46237 | F47: 46238 | G47: 96-100% coverage per season | R47: =IF($A47<>"",$A47,R46) -> E8 Model Quality
B48: Retrain on full xG coverage | C48: Done | D48: ML | E48: 46238 | F48: 46238 | G48: O/U buckets monotonic, z=+1.86 (p=0.062) | R48: =IF($A48<>"",$A48,R47) -> E8 Model Quality
B49: League-identity features — NEGATIVE result | C49: Done | D49: ML | E49: 46238 | F49: 46238 | G49: Made it worse; built, measured, disabled, documented | R49: =IF($A49<>"",$A49,R48) -> E8 Model Quality
B50: Confirm training is deterministic | C50: Done | D50: ML | E50: 46238 | F50: 46238 | G50: Reproduced bit-for-bit; no seed noise in any comparison | R50: =IF($A50<>"",$A50,R49) -> E8 Model Quality
B51: Shot-based features from shotmap | C51: Planned | D51: ML | E51: 46239 | F51: 46242 | G51: ACTION (DEV): Last untried O/U lever; data already collected | R51: =IF($A51<>"",$A51,R50) -> E8 Model Quality
A52: E9 Data Ops | B52: TheRundown Pro upgrade | C52: Done | D52: Data | E52: 46244 | F52: 46245 | G52: Pro active: 5,000 req/month confirmed live (was 1,000). Cadence stays 6h - worst case at 3h is 134% of quota | R52: =IF($A52<>"",$A52,R51) -> E9 Data Ops
B53: Narrow odds lookahead window | C53: Planned | D53: Data | E53: 46239 | F53: 46240 | G53: ACTION (DEV): Halves per-league cost | R53: =IF($A53<>"",$A53,R52) -> E9 Data Ops
B54: Re-test API-Football European odds | C54: Done | D54: Data | E54: 46255 | F54: 46255 | G54: Merged into row 135 (same check, two entries) | K54: ◆ | R54: =IF($A54<>"",$A54,R53) -> E9 Data Ops
B55: EPL 2026-27 season opens | C55: Milestone | D55: Data | E55: 46255 | F55: 46255 | G55: WAITING: First real load test | K55: ◆ | R55: =IF($A55<>"",$A55,R54) -> E9 Data Ops
B56: API-Football renewal | C56: Milestone | D56: Data | E56: 46263 | F56: 46263 | G56: WAITING: Auto-renews | L56: ◆ | R56: =IF($A56<>"",$A56,R55) -> E9 Data Ops
B57: Fix 9 tennis DRAW outcomes | C57: Done | D57: Backend | E57: 46238 | F57: 46238 | G57: CLOSED 13 Aug: 0 DRAW outcomes remain for tennis (queried). SPORTS_WITHOUT_DRAWS now refuses to settle a tied tennis score, so they cannot come back. | R57: =IF($A57<>"",$A57,R56) -> E9 Data Ops
B58: WTA subscription + collection | C58: Blocked | D58: ML | E58: 46246 | F58: 46249 | G58: ACTION (YOU): Needs tour subscription | R58: =IF($A58<>"",$A58,R57) -> E9 Data Ops
B59: Tennis odds (fast-follow) | C59: Done | D59: Data | E59: 46249 | F59: 46252 | G59: SHIPPED via BallDontLie GOAT: DraftKings + FanDuel, direct match_id join, no fuzzy name matching | R59: =IF($A59<>"",$A59,R58) -> E9 Data Ops
B60: Tennis kickoff refresh + live derivation | C60: Done | D60: Data | E60: 46237 | F60: 46238 | G60: 26->20 estimated; rest is a provider limit | R60: =IF($A60<>"",$A60,R59) -> E9 Data Ops
B61: Injury ingest per-sport isolation | C61: Done | D61: Backend | E61: 46237 | F61: 46238 | G61: NBA stub was aborting football every 30 min | R61: =IF($A61<>"",$A61,R60) -> E9 Data Ops
B62: Commit 4 Aug work | C62: Done | D62: Platform | E62: 46239 | F62: 46239 | G62: All committed and pushed | R62: =IF($A62<>"",$A62,R61) -> E9 Data Ops
B63: Review + merge feat/tennis-atp-integration | C63: Done | D63: Platform | E63: 46239 | F63: 46240 | G63: Merged; branch deleted after verifying content identical to main | R63: =IF($A63<>"",$A63,R62) -> E9 Data Ops
B64: Push main to origin | C64: Done | D64: Platform | E64: 46240 | F64: 46240 | G64: main and origin/main both at 7d0ffd5, 0 ahead / 0 behind | R64: =IF($A64<>"",$A64,R63) -> E9 Data Ops
B65: Tennis provider decision | C65: Milestone | D65: Product | E65: 46246 | F65: 46246 | G65: WAITING: Only ~2% of matches carry a real kickoff time | J65: ◆ | R65: =IF($A65<>"",$A65,R64) -> E9 Data Ops
A66: E10 Deploy | B66: Portable artefact paths | C66: Done | D66: Platform | E66: 46245 | F66: 46245 | G66: resolve_artefact_path + scripts/stage_artefacts.py; verified in a real Linux container | R66: =IF($A66<>"",$A66,R65) -> E10 Deploy
B67: infra/ + Render blueprint | C67: Done | D67: Platform | E67: 46245 | F67: 46248 | G67: infra/render.yaml: web, worker, beat off one image | R67: =IF($A67<>"",$A67,R66) -> E10 Deploy
B68: Secrets management + env parity | C68: Done | D68: Platform | E68: 46247 | F68: 46249 | G68: CLOSED 13 Aug by the real deploy: all six credentials are sync:false in infra/render.yaml, entered in the Render dashboard, never in git. | R68: =IF($A68<>"",$A68,R67) -> E10 Deploy
B69: Monitoring + alerting (Sentry) | C69: Done | D69: Platform | E69: 46248 | F69: 46252 | G69: CLOSED: SENTRY_DSN_BACKEND provisioned, init covers API + worker + beat, and monitor_beat_tasks registers each schedule entry as a cron monitor. Uptime alerting tracked separately. | R69: =IF($A69<>"",$A69,R68) -> E10 Deploy
B70: Staging deploy + soak | C70: Done | D70: Platform | E70: 46251 | F70: 46255 | G70: SOAK PASSED from an empty DB - see the milestone row below | R70: =IF($A70<>"",$A70,R69) -> E10 Deploy
B71: watchlist table + PICK-07 | C71: Done | D71: Backend | E71: 46252 | F71: 46255 | G71: watchlist_items + uq_watchlist_user_fixture; T-60 reminder verified end-to-end, 10/10 checks | R71: =IF($A71<>"",$A71,R70) -> E10 Deploy
B72: EAS project + first mobile build | C72: Done | D72: Mobile | E72: 46253 | F72: 46258 | G72: EAS project live; dev build installed on a real Android device | R72: =IF($A72<>"",$A72,R71) -> E10 Deploy
B73: Push notifications end-to-end | C73: Done | D73: Mobile | E73: 46258 | F73: 46261 | G73: VERIFIED ON A REAL PHONE: token minted, PUT /user/push-token persisted, real push delivered | R73: =IF($A73<>"",$A73,R72) -> E10 Deploy
B74: Mobile Jest + ESLint | C74: Planned | D74: Mobile | E74: 46259 | F74: 46261 | G74: ACTION (DEV): tsc is the only check | R74: =IF($A74<>"",$A74,R73) -> E10 Deploy
B75: Production deploy - FOOTBALL | C75: Done | D75: Platform | E75: 46269 | F75: 46269 | G75: ACHIEVED 13 Aug. Five services live on Render; /stats/model serves all three sports; beat->worker chain confirmed by 100+ upcoming fixtures with 83 carrying a pick. | M75: ◆ | R75: =IF($A75<>"",$A75,R74) -> E10 Deploy
B76: Closed beta (football only) | C76: Planned | D76: Product | E76: 46272 | F76: 46283 | G76: ACTION (YOU): Real users, real feedback | R76: =IF($A76<>"",$A76,R75) -> E10 Deploy
B77: Public launch readiness review | C77: Milestone | D77: Product | E77: 46290 | F77: 46290 | G77: ACTION (YOU): Gated on beta + edge | P77: ◆ | R77: =IF($A77<>"",$A77,R76) -> E10 Deploy
B78: Merge feat/base-rate-relative-picks -> main | C78: Done | D78: Platform | E78: 46237 | F78: 46237 | G78: Fast-forward; main +25 unpushed | R78: =IF($A78<>"",$A78,R77) -> E10 Deploy
B79: Local start-up runbook + delivery board | C79: Done | D79: Product | E79: 46237 | F79: 46238 | G79: SportIQ-Local-Setup.docx | R79: =IF($A79<>"",$A79,R78) -> E10 Deploy
A80: E11 Ops Resilience | B80: dev_worker.py — worker auto-restart | C80: Done | D80: Platform | E80: 46238 | F80: 46238 | G80: PREVENTION: Celery has no --reload | R80: =IF($A80<>"",$A80,R79) -> E11 Ops Resilience
B81: code_version + /health + check_stale.py | C81: Done | D81: Platform | E81: 46238 | F81: 46238 | G81: DETECTION: caught a day-old uvicorn | R81: =IF($A81<>"",$A81,R80) -> E11 Ops Resilience
B82: Verify deploy restarts worker AND beat | C82: Done | D82: Platform | E82: 46246 | F82: 46247 | G82: CLOSED 13 Aug: the real deploy brought up sportpiq-api, -worker AND -beat, and the populated production feed proves the beat->worker chain actually ran. | R82: =IF($A82<>"",$A82,R81) -> E11 Ops Resilience
B83: GIT_SHA baked into image at build | C83: Planned | D83: Platform | E83: 46247 | F83: 46247 | G83: ACTION (DEV): No working tree in a container | R83: =IF($A83<>"",$A83,R82) -> E11 Ops Resilience
B84: Sentry + uptime alerting | C84: Planned | D84: Platform | E84: 46248 | F84: 46252 | G84: ACTION (DEV): Injury worker failed unnoticed for weeks | R84: =IF($A84<>"",$A84,R83) -> E11 Ops Resilience
B85: check_stale in CI / post-deploy smoke | C85: Planned | D85: Platform | E85: 46253 | F85: 46254 | G85: ACTION (DEV): Non-zero exit already gates it | R85: =IF($A85<>"",$A85,R84) -> E11 Ops Resilience
A86: E8 Model Quality | B86: Review external optimisation consultancy | C86: Done | D86: ML | E86: 46238 | F86: 46238 | G86: Measured their DC claim; benchmark used 2k not 8.7k fixtures | R86: =IF($A86<>"",$A86,R85) -> E8 Model Quality
A87: E8 Model Quality | B87: 4-arm experiment: OOF / HFA on full data | C87: Done | D87: ML | E87: 46238 | F87: 46238 | G87: OOF +3.8pts, -20% RPS. HFA HURTS - rejected | R87: =IF($A87<>"",$A87,R86) -> E8 Model Quality
A88: E8 Model Quality | B88: OOF stacking in train_football.py | C88: Done | D88: ML | E88: 46238 | F88: 46238 | G88: Fixes the documented Layer 2 in-sample optimism | R88: =IF($A88<>"",$A88,R87) -> E8 Model Quality
A89: E8 Model Quality | B89: Prune 7 features (25 -> 18) | C89: Done | D89: ML | E89: 46238 | F89: 46238 | G89: moneyline 0.7% populated / importance 0.000; key players x4 | R89: =IF($A89<>"",$A89,R88) -> E8 Model Quality
A90: E8 Model Quality | B90: RETRAIN: best model to date | C90: Done | D90: ML | E90: 46238 | F90: 46238 | G90: acc 0.4837, RPS 0.2151, all 4 Brier scores improved | R90: =IF($A90<>"",$A90,R89) -> E8 Model Quality
A91: E8 Model Quality | B91: Over/Under clears significance | C91: Done | D91: ML | E91: 46238 | F91: 46238 | G91: z=+2.96 p=0.0031 (was +1.86 p=0.062) - GATE IS GO | R91: =IF($A91<>"",$A91,R90) -> E8 Model Quality
A92: E11 Ops Resilience | B92: Root-cause DB connection failures | C92: Done | D92: Platform | E92: 46238 | F92: 46238 | G92: localhost -> IPv6 ::1; Docker binds IPv4 only. Pinned 127.0.0.1 | R92: =IF($A92<>"",$A92,R91) -> E11 Ops Resilience
A93: E9 Data Ops | B93: Remove now-unused key-player ingest | C93: Planned | D93: Backend | E93: 46239 | F93: 46239 | G93: ACTION (DEV): Stage 1 + injury calls still run for features nothing consumes | R93: =IF($A93<>"",$A93,R92) -> E9 Data Ops
A94: E9 Data Ops | B94: Pin 127.0.0.1 in compose/.env.example/runbook | C94: Done | D94: Platform | E94: 46239 | F94: 46239 | G94: compose + .env.example + runbook troubleshooting row | R94: =IF($A94<>"",$A94,R93) -> E9 Data Ops
A95: E8 Model Quality | B95: Collect historical closing odds | C95: Planned | D95: Data | E95: 46240 | F95: 46240 | G95: ACTION (DEV): Strongest known predictor, currently 59 of 8,718 rows | R95: =IF($A95<>"",$A95,R94) -> E8 Model Quality
A96: E8 Model Quality | B96: Probe TheStatsAPI for 4 European leagues | C96: Done | D96: ML | E96: 46238 | F96: 46238 | G96: Caught 2 lower-division traps: '2. Bundesliga', 'LaLiga 2' | R96: =IF($A96<>"",$A96,R95) -> E8 Model Quality
A97: E8 Model Quality | B97: Game logs: Bundesliga/Serie A/La Liga/Ligue 1 | C97: Done | D97: Data | E97: 46238 | F97: 46238 | G97: 7,028 fixtures. Pool 8,718 -> 15,746 (+81%) | R97: =IF($A97<>"",$A97,R96) -> E8 Model Quality
... A153: E5 ML Tennis | B153: Serve-stat features - BLOCKED on GOAT tier | C153: Done | D153: Data | E153: 46254 | F153: 46254 | G153: UNBLOCKED - GOAT active. /match_stats collected: 138,219 rows, 64,266 matches, 0% nulls | R153: =IF($A153<>"",$A153,R152) -> E5 ML Tennis
A154: E5 ML Tennis | B154: BallDontLie GOAT tier active (ATP) | C154: Done | D154: Data | E154: 46243 | F154: 46243 | G154: ACHIEVED - confirmed on the APIs & Quotas sheet (GOAT, 600 req/min). The 600/min budget is what made the 2,000-row surface backfill affordable on 13 Aug. | I154: X | R154: =IF($A154<>"",$A154,R153) -> E5 ML Tennis
A155: E5 ML Tennis | B155: ATP serve-stat collection | C155: Done | D155: Data | E155: 46243 | F155: 46243 | G155: 138,219 rows / 64,266 matches / 2007-2026; 17,434 in the 2021-25 window at 0% nulls. Two independent passes agree exactly | I155: X | R155: =IF($A155<>"",$A155,R154) -> E5 ML Tennis
A156: E5 ML Tennis | B156: DECISION: total games NOT built (gate failed) | C156: Done | D156: ML | E156: 46243 | F156: 46243 | G156: Serve features are 2.5x stronger than anything prior and still no edge: at real lines 21.5 -0.0004, 22.5 +0.0040, 23.5 -0.0274. Predictions compress to the mean (sd 2.12 vs reality 7.87). ~1 week of build avoided | I156: X | R156: =IF($A156<>"",$A156,R155) -> E5 ML Tennis
...

Sheet Architecture
A1: SportIQ — End-to-End Architecture
A2: Data flows top to bottom. Green = live and working Amber = works with a real gap Red = stubbed or blocked. Offline training track shown separately at the foot.
A4: 1 · EXTERNAL DATA PROVIDERS
A5: Vendors | B5: API-Football (Ultra) fixtures • team stats • injuries H2H • lineups • corners ENDS 2026-09-29 | E5: TheRundown odds: NBA + 5 EU + MLS HEALTHY 5,000/mon | H5: BallDontLie NBA stats · ATP tennis WTA 401 — unsubscribed | K5: TheStatsAPI xG · shotmaps · shots collection in progress | N5: RotoWire NBA injuries NO KEY PROVISIONED | Q5: SportsDataIO / Highlightly Phase 2 US sports · video NOT INTEGRATED
B6: ▼
A7: 2 · ADAPTER LAYER — every provider call goes through here, never direct from a worker
A8: Abstraction | B8: DataSourceAdapter (ABC) fetch_fixtures · fetch_odds fetch_team_stats · fetch_injuries | K8: AdapterFactory routes by sport slug per-adapter error isolation
B9: ▼
A10: 3 · INGESTION & INFERENCE WORKERS (Celery + beat, Redis broker)
A11: Scheduled jobs | B11: ingest_fixtures daily 02:00 UTC ±7 days · features · Elo | E11: ingest_odds every 6h · 3-day window only dates with fixtures | H11: ingest_live_scores every 5 min scores · status · settlement | K11: ingest_injuries every 30 min per-sport isolation (fixed) | N11: run_predictions on new fixture + injury re-inference | Q11: backfill_predictions retrodiction leakage-safe game log
B12: ▼
A13: 4 · STORAGE
A14: Persistence | B14: PostgreSQL 16 fixtures · teams · odds · predictions outcomes · users · team_features | H14: Redis 7 pick cache · guest sessions (24h) Celery broker | N14: models_registry active model per sport promotion = DB update | Q14: ml/artifacts joblib model files (absolute path — deploy risk)
B15: ▲ features read ▼ predictions written
A16: 5 · ML / INFERENCE
A17: Serving | B17: Feature assembly football (18) • nba (16) • tennis (14) train/serve parity enforced | H17: FootballModel Poisson xG ×2 → XGB 1X2 + corners regressors | K17: NBAModel / TennisModel XGB binary + isotonic 2-outcome, no draw | N17: markets.py double chance · O/U goals O/U corners (Poisson) | Q17: Calibration isotonic per class + xG rate calibrators
B18: ▼
A19: 6 · API — FastAPI + Uvicorn
A20: REST | B20: /fixtures · /picks best pick across 4 markets min_probability · min_odds | H20: /history · /stats/model settled performance vs training metrics | N20: /auth · /guest · /user Argon2id · JWT + refresh guest → account migration
B21: ▼
A22: 7 · MOBILE CLIENT — Expo / React Native (the only client)
A23: App | B23: Picks tab day navigator · sport / status filters · league grouping | H23: Live tab in-play fixtures | K23: Profile prefs · theme · push · biometrics | N23: Fixture detail probability bar · H2H panel other markets | Q23: Push notifications code real • EAS project linked no EXPO_ACCESS_TOKEN yet
A26: OFFLINE TRAINING TRACK — run locally, never from a production worker
A27: Pipeline | B27: collect_*_data.py API-Football · BallDontLie nba_api (local only) | E27: collect_thestatsapi_xg.py xG + cross-provider join date+score, name tiebreak | H27: ml/data/*.parquet game logs · lineups corners · xG | K27: train_*.py Optuna → calibration → joblib artefact | N27: MLflow runs · metrics local store | Q27: models_registry row is_active flip promotes no redeploy needed
A30: ARCHITECTURAL NOTES
A31: • Sport-agnostic by design — every core table is keyed by sport_id; adding a sport is a config/data insert, not a schema change.
A32: • Model promotion is a DB update (models_registry.is_active), never a redeploy — TDD §3.1.
A33: • Train/serve parity is enforced in one module per sport: assemble_from_game_log and assemble_from_live_db must stay in lock-step.
A34: • Historical (box-score) key-player logic is kept OUT of app/models_ml/ so it can never be imported into the live path — target-leakage guard.
A35: • Per-item error isolation is now the default in every provider loop: one league or sport failing must not abort the rest.
A36: • nba_api is offline-only — stats.nba.com blocks all cloud IPs, so it must never run from a production worker.
A37: ⚠ DEPLOYMENT GAP: nothing is deployed. No infra/, artefact paths are absolute Windows paths, no monitoring, no EAS build.
A39: Legend | B39: Live & working | E39: Real gap | H39: Stubbed / blocked | K39: Datastore | N39: ML | Q39: API / App
A41: 8 • RUNTIME • Render (production, live 13 Aug 2026)
A42: Deployed | B42: sportpiq-api (web) gunicorn • binds $PORT alembic in preDeployCommand | H42: sportpiq-worker Celery prefork executes every task | K42: sportpiq-beat EXACTLY ONE, ever two would double-spend quota | N42: sportpiq-db (PG16) sportpiq-redis managed, private network | Q42: Models baked into the image stage_artefacts + manifest seed_model_registry on a new DB
A43: Local celery must stay OFF while production runs: both hit the same metered providers, and TheRundown is 5,000 per MONTH. Promotion is no longer a DB flip -- retrain, stage, commit, redeploy, seed.

Sheet Epic Summary
A1: Epic Summary
A3: Epic | B3: Total | C3: Done | D3: In progress / Planned | E3: Blocked | F3: % Complete
A4: E1 Foundation | B4: =C4+D4+E4 -> 4 | C4: =COUNTIFS('Delivery Board'!$R$5:$R$500,$A4,'Delivery Board'!$C$5:$C$500,"Done") -> 4 | D4: =COUNTIFS('Delivery Board'!$R$5:$R$500,$A4,'Delivery Board'!$C$5:$C$500,"Planned")+COUNTIFS('Delivery Board'!$R$5:$R$500,$A4,'Delivery Board'!$C$5:$C$500,"In progress")+COUNTIFS('Delivery Board'!$R$5:$R$500,$A4,'Delivery Board'!$C$5:$C$500,"Milestone") -> 0 | E4: =COUNTIFS('Delivery Board'!$R$5:$R$500,$A4,'Delivery Board'!$C$5:$C$500,"Blocked") -> 0 | F4: =IF(B4=0,0,C4/B4) -> 1
A5: E2 Ingestion | B5: =C5+D5+E5 -> 14 | C5: =COUNTIFS('Delivery Board'!$R$5:$R$500,$A5,'Delivery Board'!$C$5:$C$500,"Done") -> 13 | D5: =COUNTIFS('Delivery Board'!$R$5:$R$500,$A5,'Delivery Board'!$C$5:$C$500,"Planned")+COUNTIFS('Delivery Board'!$R$5:$R$500,$A5,'Delivery Board'!$C$5:$C$500,"In progress")+COUNTIFS('Delivery Board'!$R$5:$R$500,$A5,'Delivery Board'!$C$5:$C$500,"Milestone") -> 1 | E5: =COUNTIFS('Delivery Board'!$R$5:$R$500,$A5,'Delivery Board'!$C$5:$C$500,"Blocked") -> 0 | F5: =IF(B5=0,0,C5/B5) -> 0.92857143
A6: E3 ML NBA | B6: =C6+D6+E6 -> 5 | C6: =COUNTIFS('Delivery Board'!$R$5:$R$500,$A6,'Delivery Board'!$C$5:$C$500,"Done") -> 5 | D6: =COUNTIFS('Delivery Board'!$R$5:$R$500,$A6,'Delivery Board'!$C$5:$C$500,"Planned")+COUNTIFS('Delivery Board'!$R$5:$R$500,$A6,'Delivery Board'!$C$5:$C$500,"In progress")+COUNTIFS('Delivery Board'!$R$5:$R$500,$A6,'Delivery Board'!$C$5:$C$500,"Milestone") -> 0 | E6: =COUNTIFS('Delivery Board'!$R$5:$R$500,$A6,'Delivery Board'!$C$5:$C$500,"Blocked") -> 0 | F6: =IF(B6=0,0,C6/B6) -> 1
A7: E4 ML Football | B7: =C7+D7+E7 -> 10 | C7: =COUNTIFS('Delivery Board'!$R$5:$R$500,$A7,'Delivery Board'!$C$5:$C$500,"Done") -> 9 | D7: =COUNTIFS('Delivery Board'!$R$5:$R$500,$A7,'Delivery Board'!$C$5:$C$500,"Planned")+COUNTIFS('Delivery Board'!$R$5:$R$500,$A7,'Delivery Board'!$C$5:$C$500,"In progress")+COUNTIFS('Delivery Board'!$R$5:$R$500,$A7,'Delivery Board'!$C$5:$C$500,"Milestone") -> 1 | E7: =COUNTIFS('Delivery Board'!$R$5:$R$500,$A7,'Delivery Board'!$C$5:$C$500,"Blocked") -> 0 | F7: =IF(B7=0,0,C7/B7) -> 0.9
A8: E5 ML Tennis | B8: =C8+D8+E8 -> 24 | C8: =COUNTIFS('Delivery Board'!$R$5:$R$500,$A8,'Delivery Board'!$C$5:$C$500,"Done") -> 24 | D8: =COUNTIFS('Delivery Board'!$R$5:$R$500,$A8,'Delivery Board'!$C$5:$C$500,"Planned")+COUNTIFS('Delivery Board'!$R$5:$R$500,$A8,'Delivery Board'!$C$5:$C$500,"In progress")+COUNTIFS('Delivery Board'!$R$5:$R$500,$A8,'Delivery Board'!$C$5:$C$500,"Milestone") -> 0 | E8: =COUNTIFS('Delivery Board'!$R$5:$R$500,$A8,'Delivery Board'!$C$5:$C$500,"Blocked") -> 0 | F8: =IF(B8=0,0,C8/B8) -> 1
A9: E6 Picks | B9: =C9+D9+E9 -> 18 | C9: =COUNTIFS('Delivery Board'!$R$5:$R$500,$A9,'Delivery Board'!$C$5:$C$500,"Done") -> 16 | D9: =COUNTIFS('Delivery Board'!$R$5:$R$500,$A9,'Delivery Board'!$C$5:$C$500,"Planned")+COUNTIFS('Delivery Board'!$R$5:$R$500,$A9,'Delivery Board'!$C$5:$C$500,"In progress")+COUNTIFS('Delivery Board'!$R$5:$R$500,$A9,'Delivery Board'!$C$5:$C$500,"Milestone") -> 2 | E9: =COUNTIFS('Delivery Board'!$R$5:$R$500,$A9,'Delivery Board'!$C$5:$C$500,"Blocked") -> 0 | F9: =IF(B9=0,0,C9/B9) -> 0.88888889
A10: E7 Mobile | B10: =C10+D10+E10 -> 32 | C10: =COUNTIFS('Delivery Board'!$R$5:$R$500,$A10,'Delivery Board'!$C$5:$C$500,"Done") -> 28 | D10: =COUNTIFS('Delivery Board'!$R$5:$R$500,$A10,'Delivery Board'!$C$5:$C$500,"Planned")+COUNTIFS('Delivery Board'!$R$5:$R$500,$A10,'Delivery Board'!$C$5:$C$500,"In progress")+COUNTIFS('Delivery Board'!$R$5:$R$500,$A10,'Delivery Board'!$C$5:$C$500,"Milestone") -> 4 | E10: =COUNTIFS('Delivery Board'!$R$5:$R$500,$A10,'Delivery Board'!$C$5:$C$500,"Blocked") -> 0 | F10: =IF(B10=0,0,C10/B10) -> 0.875
A11: E8 Model Quality | B11: =C11+D11+E11 -> 65 | C11: =COUNTIFS('Delivery Board'!$R$5:$R$500,$A11,'Delivery Board'!$C$5:$C$500,"Done") -> 61 | D11: =COUNTIFS('Delivery Board'!$R$5:$R$500,$A11,'Delivery Board'!$C$5:$C$500,"Planned")+COUNTIFS('Delivery Board'!$R$5:$R$500,$A11,'Delivery Board'!$C$5:$C$500,"In progress")+COUNTIFS('Delivery Board'!$R$5:$R$500,$A11,'Delivery Board'!$C$5:$C$500,"Milestone") -> 4 | E11: =COUNTIFS('Delivery Board'!$R$5:$R$500,$A11,'Delivery Board'!$C$5:$C$500,"Blocked") -> 0 | F11: =IF(B11=0,0,C11/B11) -> 0.93846154
A12: E9 Data Ops | B12: =C12+D12+E12 -> 47 | C12: =COUNTIFS('Delivery Board'!$R$5:$R$500,$A12,'Delivery Board'!$C$5:$C$500,"Done") -> 37 | D12: =COUNTIFS('Delivery Board'!$R$5:$R$500,$A12,'Delivery Board'!$C$5:$C$500,"Planned")+COUNTIFS('Delivery Board'!$R$5:$R$500,$A12,'Delivery Board'!$C$5:$C$500,"In progress")+COUNTIFS('Delivery Board'!$R$5:$R$500,$A12,'Delivery Board'!$C$5:$C$500,"Milestone") -> 9 | E12: =COUNTIFS('Delivery Board'!$R$5:$R$500,$A12,'Delivery Board'!$C$5:$C$500,"Blocked") -> 1 | F12: =IF(B12=0,0,C12/B12) -> 0.78723404
A13: E10 Deploy | B13: =C13+D13+E13 -> 36 | C13: =COUNTIFS('Delivery Board'!$R$5:$R$500,$A13,'Delivery Board'!$C$5:$C$500,"Done") -> 33 | D13: =COUNTIFS('Delivery Board'!$R$5:$R$500,$A13,'Delivery Board'!$C$5:$C$500,"Planned")+COUNTIFS('Delivery Board'!$R$5:$R$500,$A13,'Delivery Board'!$C$5:$C$500,"In progress")+COUNTIFS('Delivery Board'!$R$5:$R$500,$A13,'Delivery Board'!$C$5:$C$500,"Milestone") -> 3 | E13: =COUNTIFS('Delivery Board'!$R$5:$R$500,$A13,'Delivery Board'!$C$5:$C$500,"Blocked") -> 0 | F13: =IF(B13=0,0,C13/B13) -> 0.91666667
A14: E11 Ops Resilience | B14: =C14+D14+E14 -> 32 | C14: =COUNTIFS('Delivery Board'!$R$5:$R$500,$A14,'Delivery Board'!$C$5:$C$500,"Done") -> 28 | D14: =COUNTIFS('Delivery Board'!$R$5:$R$500,$A14,'Delivery Board'!$C$5:$C$500,"Planned")+COUNTIFS('Delivery Board'!$R$5:$R$500,$A14,'Delivery Board'!$C$5:$C$500,"In progress")+COUNTIFS('Delivery Board'!$R$5:$R$500,$A14,'Delivery Board'!$C$5:$C$500,"Milestone") -> 4 | E14: =COUNTIFS('Delivery Board'!$R$5:$R$500,$A14,'Delivery Board'!$C$5:$C$500,"Blocked") -> 0 | F14: =IF(B14=0,0,C14/B14) -> 0.875
A16: OVERALL | B16: =SUM(B4:B14) -> 287 | C16: =SUM(C4:C14) -> 258 | D16: =SUM(D4:D14) -> 28 | E16: =SUM(E4:E14) -> 1 | F16: =IF(B16=0,0,C16/B16) -> 0.8989547
A18: Unassigned (should be 0) | B18: =COUNTIFS('Delivery Board'!$R$5:$R$500,"<>",'Delivery Board'!$C$5:$C$500,"Done")+COUNTIFS('Delivery Board'!$R$5:$R$500,"<>",'Delivery Board'!$C$5:$C$500,"Planned")+COUNTIFS('Delivery Board'!$R$5:$R$500,"<>",'Delivery Board'!$C$5:$C$500,"In progress")+COUNTIFS('Delivery Board'!$R$5:$R$500,"<>",'Delivery Board'!$C$5:$C$500,"Milestone")+COUNTIFS('Delivery Board'!$R$5:$R$500,"<>",'Delivery Board'!$C$5:$C$500,"Blocked")-B16 -> 0
A19: Auto-calculated from the Delivery Board. Add an epic here if 'Unassigned' is ever non-zero.

Sheet Risks & Decisions
A1: Risks, Blockers & Open Decisions
A3: Item | B3: Type | C3: Impact | D3: Status | E3: Action / Owner decision
A4: Model edge is unproven | B4: Risk | C4: Critical | D4: Open | E4: 1X2 +1.9pp over baseline; O/U ~base-rate. Retrain with xG is the decision point.
A5: Over/Under surfaced most, has least signal | B5: Risk | C5: High | D5: Open | E5: GO/NO-GO 2026-08-10 — surface fewer markets rather than ship confident-looking noise.
A6: Not deployed anywhere | B6: Blocker | C6: Critical | D6: Planned | E6: No infra/, absolute Windows artefact path. ~2-4 weeks of work.
A7: No monitoring — silent failures | B7: Risk | C7: High | D7: Planned | E7: Injury worker failed for weeks unnoticed; Docker down looked like an app bug.
A8: TheRundown quota exhausted | B8: Blocker | C8: Medium | D8: Decision | E8: Pro $99.99/mo before EPL opens 21 Aug, or narrow + stay on Basic.
A9: API-Football is a single point of failure | B9: Risk | C9: High | D9: Accepted | E9: Fixtures, stats, injuries, H2H, lineups all from one vendor. Auto-renews.
A10: European odds may need no vendor at all | B10: Opportunity | C10: Medium | D10: Open | E10: Re-test coverage.odds on 21 Aug; could make TheRundown NBA-only.
A11: No EAS project | B11: Blocker | C11: High | D11: Planned | E11: Cannot ship the app to a single user, nor mint push tokens.
A12: WTA blocked on subscription | B12: Blocker | C12: Low | D12: Deferred | E12: Code written and unit-tested; needs that tour subscribed.
A13: NBA injuries dead (no RotoWire key) | B13: Blocker | C13: Medium | D13: Deferred | E13: player_injury_status stays empty; NBA key-player features never vary.
A14: Mobile has no Jest/ESLint | B14: Risk | C14: Medium | D14: Planned | E14: tsc is the only automated mobile check.
... A119: Estimated-kickoff fixtures are now live-computed for a day longer | B119: Risk | C119: Low | D119: Monitored | E119: The cost of the fix, stated rather than buried: an estimated-kickoff fixture is no longer frozen until its placeholder day ends, so its card can move during that window -- the mutability the freeze exists to prevent. Right side to err on when the alternative is a card frozen permanently blank, but watch for a tennis card visibly changing within its match day.

Sheet Edge Measurement
A1: SportIQ — Edge Measurement Plan (P0-P3)
A2: Tracks whether the predictions actually work, which the Delivery Board deliberately does not: that tracks what was BUILT. As of 2026-08-10 there is no demonstrated betting edge — football ROI -6.4% (n=38), CLV -3.58% (n=27, market moving away from our picks), tennis +1.6pp over 'always back the higher-ranked player'. Green CI is not evidence the predictions are good.
A4: Priority | B4: Item | C4: Status | D4: Depends on | E4: Why it matters / what it answers
A5: P0 | B5: Separate real pre-game forecasts from retrodictions | C5: Done | D5: — | E5: DONE (7a611e9). predictions.kind = pre_match | retrodiction | unknown, set at write time by each path, never inferred. Timestamps could NOT substitute: regenerating 91 football predictions earlier that day reset created_at to after those kickoffs. The backfill is therefore one-directional — created_at < kickoff proves a forecast, the reverse proves nothing, so those rows are UNKNOWN rather than guessed. UNKNOWN is also the column default, so a future path that forgets to set it is excluded from skill measurement rather than silently claiming to be a forecast. Result: football 283 pre_match / 90 unknown, tennis 146 / 453.
A6: P0 | B6: Confirm capture_closing_odds is actually writing | C6: Done | D6: — | E6: DONE — and it was already working. 19 task runs this session and 1,151 odds rows stamped within 45 min of kickoff, against the n=27 the -3.58% CLV figure rests on. So CLV was computed on a stale slice, not a thin one: this is a READ problem, not a capture problem, and needs analysis rather than a build.
A7: P1 | B7: Spec what /history reports, before building it | C7: Done | D7: P0 | E7: DONE — docs/history-metrics-spec.md, written before the endpoint exists so its shape cannot be chosen after seeing which cut looks best. Defines population (pre_match only, voids excluded, unknown counted not hidden), exact metric definitions, multiple-comparisons discipline, and a hard requirement that every metric carries n, a CI and its detectable effect. Also lists what would make the endpoint MISLEADING, so it can be checked against.
A8: P1 | B8: Build GET /history over existing settled outcomes | C8: Done | D8: P0, spec | E8: DONE (53b7d2a) — and it was never a 501 stub; CLAUDE.md was stale. The endpoint has been LIVE and serving a contaminated number: /history/summary averaged both prediction paths, which measured football at 53.3% instead of 56.1% and tennis 61.7% instead of 63.6%. DOWNWARD, the opposite of the predicted direction — retrodictions score worse, not better, because assemble_from_game_log has a leakage guard and thinner features. Now pre_match by default, retrodictions behind an explicit ?kind=, excluded rows counted rather than dropped.
A9: P1 | B9: Grade the pick that was SHOWN, not a recomputed one | C9: Done | D9: P0 | E9: Resolved by pick_snapshots: /history will grade the stored snapshot rather than recomputing, so it measures the product users actually saw. Applies only to fixtures captured from 2026-08-10 onward.
A10: P2 | B10: PRE-REGISTER the verdict thresholds (SETTLED 2026-08-11, spec §9): CLV primary over accuracy on sample size (n~223-396 vs ~1,650); edge = CI excluding 0; the no-edge response pre-committed; re-read 2026-09-15 | C10: Done | D10: spec | E10: What counts as an edge, what counts as none, and what happens in each case - written before looking at results. Same discipline that made the Tier-1 and key-player calls trustworthy rather than fitted.
A11: P2 | B11: MIN_REPORTABLE_N 30 -> 93 to match the spec: the smallest n whose 95% Wilson interval is under 20 points. Excludes tennis (n=77), admits football (n=139) — set by the rule, not to fit the data | C11: Done | D11: pre-registration
A12: P2 | B12: sufficient_sample split into sufficient_sample (safe to display) + conclusive (safe to act on). One flag read as "trustworthy" when it only meant "big enough to print" | C12: Done | D12: pre-registration
A13: P2 | B13: First honest read: per sport, per market, per league | C13: Done | D13: /history | E13: DONE 13 Aug. Per-league existed for 1X2 only and per-market pooled only; per_league_market_metrics now reports both cuts crossed. Goals under-3.5 Brier spans 0.168 (J1) to 0.261 (Veikkausliiga) against a pooled 0.2096.
A14: P2 | B14: Re-read CLV at a real sample size | C14: Done | D14: P0 capture check | E14: DONE — and the CONTROL changed the reading. Favoured side -3.47% vs the side NOT favoured +0.83%, a -4.30pp gap (n=81 each). But football's control is ALSO negative (-2.40%), so a real part of the raw -3.61% is systematic price drift rather than the model. The control is not clean either: for a 3-way market it is the less-likely of home/away, usually the underdog, whose prices are longer and more volatile. Directional evidence against an edge; NOT a number to quote precisely. The naive -4.00% headline would have overstated it.
A15: P2 | B15: Do confidence tiers mean anything? | C15: Done | D15: /history | E15: ANSWERED: no, and worse than no. HIGH claims 74.1% delivers 60.9% (n=69); MEDIUM claims 57.8% delivers 68.5% (n=89) — the badge pointed users at the WEAKER set. Intervals overlap so the inversion is not established; the calibration gap is. Badge hidden from mobile (7233029), field still stored as measurement data. The push gate still fires on HIGH and is knowingly left in place — n=69 is too thin to rewrite it on, and exactly one real token exists — but it MUST be resolved before push reaches real users.
A16: P2 | B16: Re-run completeness-vs-correctness | C16: Done | D16: /history | E16: DONE: <0.25 33.3% (n=9), 0.25-0.35 37.5% (n=16), >=0.35 69.9% (n=123). The floor works, but the real break is at 0.35 — where mobile's own LOW_CONFIDENCE_COMPLETENESS already sits. The 0.25 choice was defensible on the extremeness evidence used at the time (85% of picks below it were >=0.90 confident vs 6% above); correctness points higher. NOT changed: n=16 in the middle band, and the decision belongs with the pre-registration rather than to whoever is looking at the data.
A17: P3 | B17: Decide Over/Under's future on the evidence — DONE 2026-08-11, and it split in two: goals_total n=242 r=+0.049 (0.2% of variance) is barred from winning the headline pick; corners_total n=234 r=+0.288 (8.3%, ~4.4 SE from zero) is KEPT. Decidable without the CLV read | C17: Done | D17: P2 read | E17: Already measured as near-base-rate (predicted xG vs actual goals r=+0.030). The open question is not how to improve it but whether to keep surfacing it as a confident pick.
A18: P3 | B18: Let the measurement inform the 22 Sep renewal | C18: Milestone | D18: P2 read | E18: API-Football ends 2026-09-29. Renewing to collect more history is a different decision from renewing to serve a working product.
A19: HOLD | B19: No new leagues until measurement lands | C19: Hold | D19: — | E19: Nine were added this week. More widens coverage of something whose value is unproven.
A20: HOLD | B20: No new markets until measurement lands | C20: Hold | D20: — | E20: Corners and O/U are already surfaced without evidence they are worth backing.
A21: HOLD | B21: No retrains chasing accuracy | C21: Hold | D21: — | E21: Three retrains in two days moved the headline by noise. The binding constraint is signal and evidence, not tuning.
A23: P0 | B23: FINDING: the sample cannot yet answer the question | C23: Done | D23: power analysis | E23: Measured after closing P0. At 80% power, n=139 football detects only a 10.5pp edge and we believe ours is 4.1pp — 891 graded pre-match picks needed, 6x what exists. Tennis is far worse: 1.6pp believed edge needs ~5,406, against 79 (68x). CONSEQUENCE: the first /history read cannot conclude anything about edge. Build it as instrumentation that accumulates, and expect a real verdict in months, not days. Anyone reading an early number as proof either way is reading noise.
A24: P1 | B24: Set expectations: /history is instrumentation, not a verdict | C24: Done | D24: the finding above | E24: DONE. Every accuracy now carries n, a 95% Wilson interval and its minimum detectable effect. Live: football n=139 acc 0.561 CI [0.478,0.641] detectable 0.105; tennis n=77 acc 0.636 CI [0.525,0.735] detectable 0.136. The intervals are the point — football's spans 16 points and its detectable effect dwarfs the 4.1pp edge we believe in, so the number cannot settle the question either way.
A25: P1 | B25: FINDING: the pick we SHOW is never persisted | C25: Done | D25: spec §2b | E25: RESOLVED by pick_snapshots (8f794e0). Product-skill metrics accumulate from 2026-08-10; nothing before it is recoverable.
... A27: P2 | B27: Push gate no longer uses the confidence tier | C27: Done | D27: pre-registration | E27: DONE (6bd3582). Replaced with the FEED'S OWN selection (_bulk_best_picks), not a new threshold — n=69 was far too thin to invent one, and doing so was explicitly refused for the completeness floor on n=16. A push can now only be sent for a pick the app itself would surface. Removing the gate outright was not an option: best_outcome returns something for almost any priced fixture. Also fixed a real incoherence found while reading the flow — the old path used h2h-only best_outcome while the card shows the best pick ACROSS markets, so a push could say 'back home' while the app showed 'UNDER 3.5' for the same fixture.
A28: P0 | B28: FINDING: the snapshot pipeline was never running. Worker and beat launched 3h BEFORE snapshot_picks.py was written, so the running beat had no snapshot entry — one row (a manual test call) in 24h. Third instance of the stale-process trap; restarted and verified through the real broker | C28: Done | D28: pick snapshots
A29: P2 | B29: VALIDATED §9.7: 79% of upcoming fixtures yield a pick; 34% of settled ones carry odds, so ~53 CLV-eligible/week reaches n=223 in 4-5 weeks. The 2026-09-15 re-read date holds and is slightly conservative | C29: Done | D29: pre-registration
A30: P2 | B30: FINDING: odds coverage is fixture-binary and the whole gap was the 9 Tier-1 leagues (7 at ZERO). NOT a bug — added 08-09 with historically-backfilled fixtures that never passed a live odds window. All 9 report coverage.odds=true and 8 returned real prices on demand | C30: Done | D30: CLV sample size
A31: P1 | B31: Beat now publishes its own code fingerprint (beat_init) and check_stale reports it. The blind spot was exactly where the damage was: only the worker published, so a stale SCHEDULER read as "ok". Both processes moved onto dev_worker.py, which restarts on change | C31: Done | D31: the snapshot finding
A32: P1 | B32: Guard: every scheduled task must belong to a module the worker imports, and the snapshot entry is pinned by name — the whole pre-registration rests on one beat_schedule line whose absence is silent | C32: Done | D32: beat liveness
A33: P1 | B33: Sentry wired into the Celery worker and beat, not just the API — it had only ever been initialised in create_app(), so every silent worker failure this project has had was unreportable. One shared initialiser; events tagged with component + loaded code fingerprint | C33: Done | D33: the snapshot finding
A34: P1 | B34: monitor_beat_tasks makes each beat_schedule entry a Sentry cron monitor, so a scheduled task that STOPS ARRIVING alerts. The one failure ordinary error reporting cannot catch: no exception, no failed task, no log line — the work just never happens | C34: Done | D34: Sentry wiring
A35: P2 | B35: SENTRY_DSN_BACKEND now populated in backend/.env (gitignored). The DSN existed in keys.docx from the start — it had simply never reached the environment the app reads. Verified: init_sentry True, test event accepted, transport flushed | C35: Done | D35: user action
A36: P1 | B36: Tennis odds were stale up to 6h: the hourly job used BallDontLie only (4 matches priced) while TheRundown (31 ATP events, all unmasked) arrived only on the shared 6-hourly run. Given its own 2-hourly job — ~720 calls/mo vs ~1,440 hourly, which would not fit alongside football's expected ~3,600. One day went 4 of 28 priced -> 24 of 28 | C36: Done | D36: odds coverage
A37: P2 | B37: NOTE: odds make the feed SMALLER, not larger — that day went 8 fixtures to 4. min_odds can only apply where a price exists, and tennis favourites at ~0.70 price below a 1.50 floor. Those cards previously showed because the filter silently could not apply | C37: Done | D37: odds coverage
A38: P3 | B38: Football empty cards are NOT a fault: ODDS_LOOKAHEAD_DAYS=3 and no football fixture is currently inside 3 days. Recheck once the European seasons open on 21 Aug | C38: Done | D38: odds coverage
A39: P1 | B39: PERSON-name matching for tennis odds: the lookup was exact + case-sensitive, so 4 fixtures with real prices showed empty cards (SoonWoo vs Soonwoo; Wu Yibing vs Yibing Wu; Chak Lam Coleman Wong). Token-SET match needing >=2 shared tokens, opt-in per sport. 24 of 28 -> 28 of 28 priced; model/market agree on the favourite in 21 of 28 | C39: Done | D39: odds coverage
... A55: MODEL | B55: Seed now genuinely load-bearing: the tuned config uses subsample 0.88 / colsample 0.63, so training is stochastic for the first time. Pinning it in #2 before this landed is what keeps runs comparable | C55: Done | D55: #2/#4
A56: MODEL | B56: FOLLOW-UP: the corners Poisson regressors are still untuned (MAE unchanged at 2.156, which confirms the scoping). Same pattern as Layer 1 would apply | C56: Done | D56: #5 | E56: DONE 13 Aug. Tuned against validation Poisson deviance, and the Over/Under CORNERS market got its first held-out evaluation at the same time - it had shipped judged by MAE alone while the product sold P(under 9.5).
A57: MODEL | B57: goals_total re-admission TRIGGER is now CHECKED AUTOMATICALLY, not remembered: app/predictions/market_signal.py holds the pre-registered thresholds (n>=200, r>=+0.15, 95% CI low > +0.05 on SETTLED pre-match predictions from football_xgb_v20260812080921 onward) and a weekly Celery task reports status, logging WARNING + a Sentry message when met | C57: Done | D57: O/U
A58: MODEL | B58: The check deliberately does NOT lift the bar itself — re-admitting a market changes what users are told to back, so that stays a human decision. Pinned by a test that the worker never imports the pick-selection set | C58: Done | D58: O/U
A59: MODEL | B59: Same correlation function now used by BOTH the training run (test-set read, printed + logged to MLflow) and the live trigger, so the two cannot drift and a market cannot be re-admitted on evidence that does not match the bar that barred it | C59: Done | D59: O/U
A60: MODEL | B60: STATUS at wiring time: n=0 — the tuned model has no settled predictions yet. ~90 football fixtures settle per week and 125 are scheduled in the next 14 days, so the trigger becomes answerable around the 2026-09-15 CLV re-read | C60: Planned | D60: O/U
A61: MOBILE | B61: Missing country flags fixed — Norway, Finland, Denmark, Poland, Czech-Republic all rendered the globe fallback since the Tier-1 league expansion. Real PNGs added; verified in the running app on 9 Aug: 12 distinct flags render, ZERO globes remain | C61: Done | D61: user report
A62: MOBILE | B62: Guard added (backend/tests/test_league_flags.py): every seeded league country must have a flag, and every referenced PNG must exist. Adding a league is a data insert by design, which is exactly why the flag gets forgotten — and a missing one produces no error, warning or log | C62: Done | D62: user report
A63: MOBILE | B63: NOTE: the guard caught a real miss immediately — the normalising fallback for API-Football's hyphenated 'Czech-Republic' had silently failed to apply; only the exact map key landed. Flags worked, but the intended safety net did not exist | C63: Done | D63: user report
A64: MODEL | B64: FULL-SCORELINE LOG LOSS added to every training run, against two model-free references (empirical joint vs the same data with dependence removed). This was the good part of the bivariate-Poisson critique and it tests the CONDITIONAL claim that unconditional dispersion figures cannot | C64: Done | D64: O/U structure
A65: MODEL | B65: RESULT: value of modelling dependence AT ALL = +0.0005 nats — the ceiling for any bivariate Poisson or Dixon-Coles. Our model beats the dependence-aware reference by 0.0835, so per-fixture conditioning is worth ~167x the entire dependence structure. NO new score model | C65: Done | D65: O/U structure
A66: MODEL | B66: Per-league dispersion re-measured on 27,914 fixtures: 9 of 18 leagues UNDERdispersed (incl. EPL, Serie A, Bundesliga) so a negative binomial is inadmissible; 15 of 18 have NEGATIVE home/away correlation so a bivariate Poisson cannot express the sign | C66: Done | D66: O/U structure
A67: BUG | B67: THIRD recurrence of "cancelled game still active" fixed at the mechanism, not the symptom. Estimated-kickoff threshold 48h -> 30h, and now DERIVED (24h for the day the placeholder stands for + 6h late-finish grace) rather than guessed. 48 allowed a full extra day after the day had already ended | C67: Done | D67: user report
A68: BUG | B68: Self-monitoring added: _warn_if_stale_fixtures_remain counts fixtures the sweep should have caught and logs WARNING to Sentry. All three recurrences were invisible to us — a too-generous threshold looks exactly like a working sweep unless something counts leftovers | C68: Done | D68: user report
... A72: MODEL | B72: DEVIATION RECORDED: n=10 lost the ONE pre-registered criterion (RPS 0.2097->0.2098, 0.05% relative). The rule carried no tolerance and was badly specified; overriding it was a deliberate user-approved call, documented as an override rather than reinterpreted | C72: Done | D72: windows
A73: MODEL | B73: OPEN: NBA and tennis still use LAST_N_FORM=10 by inheritance, untested. Tennis is the more suspect — players compete in bursts, so 10 matches can span surfaces and months | C73: Done | D73: windows | E73: DONE 13 Aug. Both measured and both DEFENDED 10. All three sports now converge on 10.
A75: P1 | B75: THE MEASUREMENT MEASURED THE WRONG OBJECT: /history and the notebook graded the 1X2 argmax while the product shows best_pick across four markets | C75: Done | D75: user report | E75: Football's settled card picks are 43 double chance + 19 corners and ZERO h2h, so the published football accuracy described a market football cards never show. Grading the card moves it 0.3651 -> 0.7258 (n=62) - but the no-skill baseline rises with it to 0.6391, so the honest figure is +8.67pp against a 14.09pp detectable effect. Not conclusive.
A76: P1 | B76: grade_pick ported from TypeScript so endpoint, notebook and card cannot disagree | C76: Done | D76: card grading | E76: The four-market rule existed once, in mobile/lib/pickFormat.ts, so only the phone could say whether a card had been right. Deliberate line-by-line port including the parts that look like bugs ('12' ungraded, an exact push losing both ways).
A77: P1 | B77: 1X2 got log loss / multiclass Brier / ECE / per-class reliability | C77: Done | D77: critique | E77: The flagship market had RPS and nothing else - Over/Under goals and corners each got a reliability table only after shipping wrong. FINDING: 92% of test fixtures get a draw probability in 0.2-0.3 (observed 0.257): right on average, no per-fixture information.
A78: P2 | B78: CORRECTION: isotonic calibration on 1X2 DOES earn its place | C78: Done | D78: 1X2 metrics | E78: Reported as not earning it on log loss (1.0179 vs 1.0148) and Brier (identical). Both are the wrong instrument - the product reads the probability VALUE through min_probability, the base-rate gates and EV. ECE 0.0143 vs 0.0195 uncalibrated. Judge a component on the metric it exists for.
A79: P2 | B79: The draw finding needs no new guard - it is already contained | C79: Done | D79: 1X2 metrics | E79: MIN_EDGE_OVER_BASE_RATE requires a draw to reach 0.3038 and ZERO draw picks have ever reached a card, measured over the whole settled history.
A80: P1 | B80: Per-fixture test outputs saved, so model comparisons are a join not a memory | C80: Done | D80: critique | E80: Every comparison had rested on printed headlines plus booster hashes - enough to prove scope, useless for attribution. It is what forced the caveat that corners MAE 2.167 -> 2.157 was not an improvement because the test set grew 35%.
A81: P0 | B81: TRAP: a training run promoted itself, and the losing arm went live | C81: Done | D81: windows | E81: The tennis n=5 arm scored worse on accuracy AND RPS and became the served model by finishing. Worse than a bad number: LAST_N_FORM reads back at 10 when serving, so a model trained on 5 would have been fed 10. --no-activate added to all three scripts.
A82: P0 | B82: TRAP: --no-activate then stranded NBA with ZERO active models | C82: Done | D82: windows | E82: Mirror image of the above, from the same register-and-activate coupling. runner.py resolves the model from the registry, so the sport stops predicting with no exception anywhere. Caught only because /stats/model dropped NBA. Demotion now happens only when something replaces the incumbent.
A83: P1 | B83: A tightening guard rewrote published history | C83: Done | D83: user report | E83: MIN_FEATURE_COMPLETENESS 0.25 -> 0.35 deleted 21 already-published picks from past cards (9 Scottish Prem), because best_pick is recomputed per request. Not neutral: sub-0.35 picks run 0.2857 vs 0.5263 above, so filtering them made the record look BETTER than it is. Settled fixtures now exempt from that one guard.
A84: P0 | B84: LIVE IN PRODUCTION - the measurement now has a real population to accumulate | C84: Done | D84: deploy | E84: Deployed 13 Aug. Every number measured so far is from the LOCAL database; production starts its own history from today, so /history there will read as a new model with no record until it accumulates.
A85: P2 | B85: PRODUCTION AND LOCAL SHARE THE SAME METERED QUOTAS | C85: Done | D85: deploy | E85: Local celery (2 workers + 2 beats) was killed on 13 Aug and the dev app repointed at production, so exactly one scheduler now spends TheRundown's 5,000/month. Running local beat alongside production double-spends it.
... A87: P2 | B87: WNBA calibration against WNBA outcomes is UNMEASURED | C87: Planned | D87: WNBA live | E87: The weights are NBA's. WNBA pace, scoring level and home advantage differ, so calibration may be off in either direction; the two priced fixtures both had the model BELOW the market, which is at least not the overconfidence failure mode. Needs settled WNBA fixtures to accumulate before anything can be said. A dedicated model is possible but small: ~312 games a season against NBA's ~1,230, on a 12-feature vector.

Sheet APIs & Quotas
A1: External APIs, Quotas & Expiry
A2: All figures read live from each provider at 2026-08-09. No credentials are stored in this file.
A4: Provider | B4: What we get from it | C4: Plan / tier | D4: Quota | E4: Used (as checked) | F4: Remaining | G4: Expiry / reset | H4: Status | I4: Notes & constraints
A5: API-Football (v3, direct host) | B5: Football fixtures, team stats, injuries, lineups, corners, H2H, and Brasileirao odds. The primary football provider. | C5: Ultra | D5: 75,000 / day (450 / minute) | E5: 23,783 today | F5: 51,217 today | G5: SUBSCRIPTION ENDS 2026-09-29 | H5: HEALTHY | I5: Read live from GET /status on 2026-08-10: plan=Ultra, active=true, end=2026-09-29. CORRECTION: the sheet previously said Pro / 7,500 per day / ends 2026-08-29 and called it a 20-day hard deadline - the real end date is a month later. The 450/minute cap is the one that actually bites: a bulk collection run saturates it and then every OTHER caller gets HTTP 200 with an empty response and results=0, which reads exactly like 'this league has no data'. Do not run a live probe against a background collection.
A6: TheRundown (via RapidAPI) | B6: Odds: NBA, the 5 European football leagues, MLS, and ATP/WTA tennis. Only real source of game-totals lines. | C6: Pro | D6: 5,000 / month | E6: 68 this period | F6: 4,932 | G6: resets in ~27 days | H6: HEALTHY | I6: Upgraded from 1,000/month. Odds job stays at 6h: worst case at 3h is 134% of quota. No Brazil, Scotland or China coverage at all. Only 3 of ~15 affiliates return real prices; the rest send a 0.0001 masked sentinel.
A7: BallDontLie - ATP tennis | B7: Tennis fixtures, matches, match_stats (serve/return), odds (DraftKings + FanDuel), rankings, H2H. | C7: GOAT | D7: 600 / minute | E7: 1 (probe) | F7: 599 | G7: no expiry observed | H7: HEALTHY | I7: 10x the ALL-STAR limit. /match_stats paginates by SEASON not per fixture, so bulk history is minutes not days. NOTE: season and match_ids filters are SILENTLY IGNORED on some endpoints - always test with a nonsense value.
A8: BallDontLie - WTA tennis | B8: Nothing usable. /rankings only. | C8: Free (not subscribed) | D8: 5 / minute | E8: n/a | F8: n/a | G8: n/a | H8: BLOCKED | I8: Every endpoint except /rankings returns 401. GOAT covers ATP ONLY - WTA needs its own subscription. Code is written and unit-tested; just point league='wta' once subscribed.
A9: BallDontLie - NBA | B9: NBA fixtures and team stats for live serving. | C9: Free | D9: 5 / minute | E9: 1 (probe) | F9: 4 | G9: no expiry | H9: TIGHT | I9: /season_averages, /standings and /player_injuries all 401 on this tier. 5/min is why ingest caches per-run; fine for 30 teams, would not scale.
A10: TheStatsAPI | B10: Expected goals (xG) for football - the only xG source; API-Football supplies none at any tier. | C10: paid | D10: 120 / minute (+ a monthly cap) | E10: 0 (probe) | F10: 120 this minute | G10: monthly cap not exposed in headers | H10: WATCH | I10: Monthly quota is real and has been hit before - it reports as 'season not found', which is misleading. Per-minute limit was raised 12 -> 120; the collector now reads pacing from x-ratelimit-limit rather than a constant.
A11: nba_api (stats.nba.com) | B11: NBA historical training data only. | C11: free | D11: unthrottled | E11: n/a | F11: n/a | G11: none | H11: LOCAL ONLY | I11: Blocks ALL cloud-provider IPs at the network level. Must never be called from a production worker - offline training only.
A12: Expo Push API | B12: Delivering push notifications to devices. | C12: unauthenticated | D12: lower unauthenticated rate limit | E12: n/a | F12: n/a | G12: none | H12: WORKS | I12: No EXPO_ACCESS_TOKEN provisioned. Sends work and were verified on a real device. Ticket is returned but the RECEIPT is never checked, so delivery failures are currently invisible.
A13: RotoWire | B13: NBA injuries (intended). | C13: never provisioned | D13: n/a | E13: n/a | F13: n/a | G13: n/a | H13: NOT PROVISIONED | I13: No key was ever obtained. Adapter is a stub, so NBA player_injury_status stays empty. Football injuries come from API-Football and are real.
A14: SportsDataIO | B14: Phase 2 US sports (NFL/NHL/MLB). | C14: never provisioned | D14: n/a | E14: n/a | F14: n/a | G14: n/a | H14: NOT PROVISIONED | I14: Adapter is a stub. Not needed until Phase 2.
A16: Re-check by calling each provider's own status endpoint; do not trust these figures after the dates above. API-Football: GET /status. TheRundown: x-ratelimit-requests-* response headers. BallDontLie / TheStatsAPI: x-ratelimit-* response headers.
A18: 13 Aug: PRODUCTION IS NOW LIVE AND SHARES EVERY QUOTA ABOVE. The figures here were read from a single local machine. Render's beat is now the only scheduler that should be running - local celery was stopped the same day, because two schedulers against the same providers double-spend metered quota and TheRundown is 5,000 per MONTH.
A20: 13 Aug: BallDontLie /wnba/v1 confirmed live on the SAME key as NBA -- 200, mid-season, history past 2024. /season_averages is a 404 and /standings + /player_injuries 401, so WNBA carries no player-level data at all. TheRundown covers WNBA at sport_id 8.
